pytailer/__init__.py
pytailer/async_core.py
pytailer/core.py
pytailer-0.1.0.dist-info/WHEEL
pytailer-0.1.0.dist-info/METADATA
pytailer-0.1.0.dist-info/RECORD
